mastodon_notifications_to_email.py
mastodon_notifications_to_email-0.1.0.dist-info/licenses/LICENSE
mastodon_notifications_to_email-0.1.0.dist-info/METADATA
mastodon_notifications_to_email-0.1.0.dist-info/WHEEL
mastodon_notifications_to_email-0.1.0.dist-info/entry_points.txt
mastodon_notifications_to_email-0.1.0.dist-info/top_level.txt
mastodon_notifications_to_email-0.1.0.dist-info/RECORD
