Metadata-Version: 2.4
Name: mastodon-notifications-to-email
Version: 0.1.0
Summary: Send Mastodon/GoToSocial notifications as emails
License-Expression: MIT
Project-URL: Homepage, https://codeberg.org/eht16/mastodon_notifications_to_email
Project-URL: Bug Tracker, https://codeberg.org/eht16/mastodon_notifications_to_email/issues
Keywords: mastodon,gotosocial,notification
Classifier: Development Status :: 5 - Production/Stable
Classifier: Intended Audience :: End Users/Desktop
Classifier: Operating System :: OS Independent
Classifier: Programming Language :: Python
Classifier: Programming Language :: Python :: 3
Classifier: Topic :: Communications
Requires-Python: >=3.11
License-File: LICENSE
Requires-Dist: Mastodon.py
Requires-Dist: markdownify
Dynamic: license-file
